code_dictionary/__init__.py
code_dictionary/java_generate.py
code_dictionary/java/__init__.py
code_dictionary/java/classes.py
code_dictionary/java/fields.py
code_dictionary/java/methods.py
code_dictionary-0.3.0.dist-info/licenses/LICENSE
code_dictionary-0.3.0.dist-info/METADATA
code_dictionary-0.3.0.dist-info/WHEEL
code_dictionary-0.3.0.dist-info/top_level.txt
code_dictionary-0.3.0.dist-info/RECORD
