Metadata-Version: 2.4
Name: code-dictionary
Version: 0.3.0
Summary: Generated dicts of Programming Languages classes, fields, and methods.
Author-email: Arkadiusz Klemenko <arek.klemenko@gmail.com>
License: MIT License
Project-URL: Homepage, http://github.com/alexiej/code-dictionary
Project-URL: Issues, https://github.com/alexiej/code-dictionary/issues
Keywords: java,dictionary,bytecode,classes,fields,methods
Classifier: Programming Language :: Python :: 3
Classifier: License :: OSI Approved :: MIT License
Classifier: Operating System :: OS Independent
Requires-Python: >=3.10
License-File: LICENSE
Requires-Dist: tqdm>=4.66.0
Dynamic: license-file
